CHANGES.rst
LICENSE
MANIFEST.in
README.rst
setup.cfg
setup.py
nihao_pypi/__init__.py
nihao_pypi/__version__.py
nihao_pypi/nihao.py
nihao_pypi.egg-info/PKG-INFO
nihao_pypi.egg-info/SOURCES.txt
nihao_pypi.egg-info/dependency_links.txt
nihao_pypi.egg-info/requires.txt
nihao_pypi.egg-info/top_level.txt
requirements/base.txt
requirements/ci.txt
requirements/test.txt
requirements/tox.txt